pydantic_string_url/__init__.py
pydantic_string_url/py.typed
pydantic_string_url-1.0.1.dist-info/LICENSE
pydantic_string_url-1.0.1.dist-info/METADATA
pydantic_string_url-1.0.1.dist-info/WHEEL
pydantic_string_url-1.0.1.dist-info/RECORD
