Metadata-Version: 2.1
Name: pydantic-string-url
Version: 1.0.1
Summary: Pydantic URL types that are based on the str class.
Home-page: https://github.com/patrsc/pydantic-string-url
License: MIT
Author: Patrick
Author-email: patrsc@nubu.at
Requires-Python: >=3.8.1,<4.0.0
Classifier: License :: OSI Approved :: MIT License
Classifier: Programming Language :: Python :: 3
Classifier: Programming Language :: Python :: 3.9
Classifier: Programming Language :: Python :: 3.10
Classifier: Programming Language :: Python :: 3.11
Requires-Dist: pydantic (>=2.0.0,<3.0.0)
Project-URL: Bug Tracker, https://github.com/patrsc/pydantic-string-url/issues
Project-URL: Documentation, https://github.com/patrsc/pydantic-string-url
Project-URL: Repository, https://github.com/patrsc/pydantic-string-url
